kachery/__init__.py
kachery/cli.py
kachery/version.txt
kachery/client/__init__.py
kachery/client/_api_requests.py
kachery/client/_compute_file_hash.py
kachery/client/_custom_storage_backend.py
kachery/client/_form_uri.py
kachery/client/_fs_operations.py
kachery/client/_json_stringify_deterministic.py
kachery/client/_load_github_file.py
kachery/client/_load_http_file.py
kachery/client/_load_sha1_file_from_cloud.py
kachery/client/_random_string.py
kachery/client/_sha1_of_dict.py
kachery/client/_sha1_of_string.py
kachery/client/cat_file.py
kachery/client/core.py
kachery/client/get_kachery_dir.py
kachery/client/load_bytes.py
kachery/client/load_file.py
kachery/client/load_file_local.py
kachery/client/mutable_local.py
kachery/client/store_file.py
kachery/client/store_file_local.py
kachery-2.0.2.dist-info/METADATA
kachery-2.0.2.dist-info/WHEEL
kachery-2.0.2.dist-info/entry_points.txt
kachery-2.0.2.dist-info/top_level.txt
kachery-2.0.2.dist-info/RECORD
